stat386_final/__init__.py
stat386_final/app.py
stat386_final/model.py
stat386_final/preprocess.py
stat386_final/read.py
stat386_final/viz.py
stat386_final/data/eu_model.pkl
stat386_final/data/eu_scaler.pkl
stat386_final/data/game_data.csv
stat386_final/data/global_model.pkl
stat386_final/data/global_scaler.pkl
stat386_final/data/jp_model.pkl
stat386_final/data/jp_scaler.pkl
stat386_final/data/na_model.pkl
stat386_final/data/na_scaler.pkl
stat386_final/data/other_model.pkl
stat386_final/data/other_scaler.pkl
stat386_final/data/pickling_models.ipynb
stat386_final/data/vgsales.csv
stat386_final-0.2.0.dist-info/licenses/LICENSE
stat386_final-0.2.0.dist-info/METADATA
stat386_final-0.2.0.dist-info/WHEEL
stat386_final-0.2.0.dist-info/top_level.txt
stat386_final-0.2.0.dist-info/RECORD
