Metadata-Version: 2.4
Name: stat386_final
Version: 0.2.0
Summary: Statistical analysis of video game sales data with preprocessing, visualization, and predictive modeling
Author: Adam Britner, Corbin Christiansen
License-Expression: MIT
Project-URL: Homepage, https://Oldarmor.github.io/Stat_386_Final_Project/
Project-URL: Repository, https://github.com/Oldarmor/Stat_386_Final_Project
Keywords: statistics,data-analysis,sales-prediction
Requires-Python: >=3.11
License-File: LICENSE
Requires-Dist: matplotlib>=3.10.7
Requires-Dist: numpy>=2.3.5
Requires-Dist: pandas>=2.3.3
Requires-Dist: requests>=2.32.5
Requires-Dist: scikit-learn>=1.7.2
Requires-Dist: seaborn>=0.13.2
Dynamic: license-file
